croissant_rdf/__init__.py
croissant_rdf/croissant_harvester.py
croissant_rdf/py.typed
croissant_rdf/utils.py
croissant_rdf/providers/__init__.py
croissant_rdf/providers/dataverse.py
croissant_rdf/providers/huggingface.py
croissant_rdf/providers/kaggle.py
croissant_rdf/providers/openml.py
croissant_rdf-0.1.2.dist-info/METADATA
croissant_rdf-0.1.2.dist-info/WHEEL
croissant_rdf-0.1.2.dist-info/entry_points.txt
croissant_rdf-0.1.2.dist-info/licenses/LICENSE
croissant_rdf-0.1.2.dist-info/RECORD
