Metadata-Version: 2.4
Name: croissant-rdf
Version: 0.1.2
Summary: Tools for working with RDF from Croissant JSON-LD resources.
Project-URL: Homepage, https://github.com/david4096/croissant-rdf
Project-URL: Documentation, https://github.com/david4096/croissant-rdf
Project-URL: History, https://github.com/david4096/croissant-rdf/releases
Project-URL: Tracker, https://github.com/david4096/croissant-rdf/issues
Project-URL: Source, https://github.com/david4096/croissant-rdf
Author-email: David Steinberg <david@resium.com>
Maintainer-email: David Steinberg <david@resium.com>
License: MIT License
License-File: LICENSE
Keywords: CroissantML,JSON-LD,RDF,SPARQL
Classifier: License :: OSI Approved :: MIT License
Classifier: Operating System :: OS Independent
Classifier: Programming Language :: Python :: 3
Requires-Python: >=3.8
Requires-Dist: huggingface-hub>=0.29.1
Requires-Dist: kaggle>=1.6.17
Requires-Dist: openml>=0.15.1
Requires-Dist: rdflib>=6.0.0
Requires-Dist: requests>=2.32.3
Requires-Dist: rich>=13.9.4
